docuwriter/__init__.py
docuwriter/core.py
docuwriter/css.py
docuwriter/js.py
docuwriter-0.0.5.dist-info/METADATA
docuwriter-0.0.5.dist-info/WHEEL
docuwriter-0.0.5.dist-info/entry_points.txt
docuwriter-0.0.5.dist-info/top_level.txt
docuwriter-0.0.5.dist-info/RECORD
